rowan/__init__.py
rowan/functions.py
rowan/calculus/__init__.py
rowan/geometry/__init__.py
rowan/interpolate/__init__.py
rowan/mapping/__init__.py
rowan/random/__init__.py
rowan-1.3.1.dist-info/LICENSE.txt
rowan-1.3.1.dist-info/METADATA
rowan-1.3.1.dist-info/WHEEL
rowan-1.3.1.dist-info/top_level.txt
rowan-1.3.1.dist-info/RECORD
