Metadata-Version: 2.1
Name: rowan
Version: 1.3.1
Summary: Perform quaternion operations using NumPy arrays
Author-email: Vyas Ramasubramani <vramasub@umich.edu>
License: rowan BSD-3 Clause Open Source Software License
Project-URL: Homepage, https://github.com/glotzerlab/rowan
Classifier: Development Status :: 6 - Mature
Classifier: License :: OSI Approved :: BSD License
Classifier: Programming Language :: Python :: 3.8
Classifier: Programming Language :: Python :: 3.9
Classifier: Programming Language :: Python :: 3.10
Classifier: Programming Language :: Python :: 3.11
Classifier: Programming Language :: Python :: 3.12
Classifier: Topic :: Scientific/Engineering :: Mathematics
Requires-Python: >=3.8
License-File: LICENSE.txt
Requires-Dist: numpy>=1.21
Provides-Extra: mapping
Requires-Dist: scipy>=1.7; extra == "mapping"
